SnakeType/SnakeType.py
SnakeType/__init__.py
snaketype-2.0.0.dist-info/licenses/LICENSE
snaketype-2.0.0.dist-info/METADATA
snaketype-2.0.0.dist-info/WHEEL
snaketype-2.0.0.dist-info/top_level.txt
snaketype-2.0.0.dist-info/RECORD
