Metadata-Version: 2.4
Name: SnakeType
Version: 2.0.0
Summary: A project, that mimics all the Typing Websites, but now in Python.
Author-email: Aarav Gupta <tribejustice35@gmail.com>
License: Apache Software License
Project-URL: Homepage, https://github.com/Aarav2709/SnakeType
Keywords: Typing,Test,Skills,Hobbies,Python
Classifier: Development Status :: 5 - Production/Stable
Classifier: License :: OSI Approved :: Apache Software License
Classifier: Programming Language :: Python :: 3.13
Classifier: Intended Audience :: Education
Classifier: Operating System :: OS Independent
Requires-Python: >=3.6
License-File: LICENSE
Dynamic: license-file
